OpenShiftGrapher/OpenShiftGrapher.py
OpenShiftGrapher/__init__.py
OpenShiftGrapher/collectors.py
openshiftgrapher-0.6.dist-info/licenses/LICENSE.txt
openshiftgrapher-0.6.dist-info/METADATA
openshiftgrapher-0.6.dist-info/WHEEL
openshiftgrapher-0.6.dist-info/entry_points.txt
openshiftgrapher-0.6.dist-info/top_level.txt
openshiftgrapher-0.6.dist-info/RECORD
