Metadata-Version: 2.4
Name: OpenShiftGrapher
Version: 0.6
Summary: Create relational databases, in neo4j, of an OpenShift cluster.
Author: Maxime de Caumia Baillenx
License-File: LICENSE.txt
Requires-Dist: py2neo
Requires-Dist: openshift
Requires-Dist: progress
Requires-Dist: pytest
Dynamic: author
Dynamic: description
Dynamic: description-content-type
Dynamic: license-file
Dynamic: requires-dist
Dynamic: summary
